{
    "info":  {
                 "name":  "Ecommerce API",
                 "schema":  "https://schema.getpostman.com/json/collection/v2.1.0/collection.json"
             },
    "item":  [
                 {
                     "name":  "admin",
                     "item":  [
                                  {
                                      "name":  "POST /api/v1/admin/products",
                                      "request":  {
                                                      "method":  "POST",
                                                      "header":  [

                                                                 ],
                                                      "url":  {
                                                                  "raw":  "{{baseUrl}}/api/v1/admin/products",
                                                                  "host":  [
                                                                               "{{baseUrl}}"
                                                                           ],
                                                                  "path":  [
                                                                               "api",
                                                                               "v1",
                                                                               "admin",
                                                                               "products"
                                                                           ]
                                                              }
                                                  }
                                  },
                                  {
                                      "name":  "GET /api/v1/admin/products",
                                      "request":  {
                                                      "method":  "GET",
                                                      "header":  [

                                                                 ],
                                                      "url":  {
                                                                  "raw":  "{{baseUrl}}/api/v1/admin/products",
                                                                  "host":  [
                                                                               "{{baseUrl}}"
                                                                           ],
                                                                  "path":  [
                                                                               "api",
                                                                               "v1",
                                                                               "admin",
                                                                               "products"
                                                                           ]
                                                              }
                                                  }
                                  },
                                  {
                                      "name":  "PUT /api/v1/admin/products/{id}",
                                      "request":  {
                                                      "method":  "PUT",
                                                      "header":  [

                                                                 ],
                                                      "url":  {
                                                                  "raw":  "{{baseUrl}}/api/v1/admin/products/{id}",
                                                                  "host":  [
                                                                               "{{baseUrl}}"
                                                                           ],
                                                                  "path":  [
                                                                               "api",
                                                                               "v1",
                                                                               "admin",
                                                                               "products",
                                                                               "{id}"
                                                                           ],
                                                                  "variable":  [
                                                                                   {
                                                                                       "key":  "id",
                                                                                       "value":  ""
                                                                                   }
                                                                               ]
                                                              }
                                                  }
                                  },
                                  {
                                      "name":  "DELETE /api/v1/admin/products/{id}",
                                      "request":  {
                                                      "method":  "DELETE",
                                                      "header":  [

                                                                 ],
                                                      "url":  {
                                                                  "raw":  "{{baseUrl}}/api/v1/admin/products/{id}",
                                                                  "host":  [
                                                                               "{{baseUrl}}"
                                                                           ],
                                                                  "path":  [
                                                                               "api",
                                                                               "v1",
                                                                               "admin",
                                                                               "products",
                                                                               "{id}"
                                                                           ],
                                                                  "variable":  [
                                                                                   {
                                                                                       "key":  "id",
                                                                                       "value":  ""
                                                                                   }
                                                                               ]
                                                              }
                                                  }
                                  },
                                  {
                                      "name":  "GET /api/v1/admin/orders",
                                      "request":  {
                                                      "method":  "GET",
                                                      "header":  [

                                                                 ],
                                                      "url":  {
                                                                  "raw":  "{{baseUrl}}/api/v1/admin/orders",
                                                                  "host":  [
                                                                               "{{baseUrl}}"
                                                                           ],
                                                                  "path":  [
                                                                               "api",
                                                                               "v1",
                                                                               "admin",
                                                                               "orders"
                                                                           ]
                                                              }
                                                  }
                                  },
                                  {
                                      "name":  "GET /api/v1/admin/orders/{id}",
                                      "request":  {
                                                      "method":  "GET",
                                                      "header":  [

                                                                 ],
                                                      "url":  {
                                                                  "raw":  "{{baseUrl}}/api/v1/admin/orders/{id}",
                                                                  "host":  [
                                                                               "{{baseUrl}}"
                                                                           ],
                                                                  "path":  [
                                                                               "api",
                                                                               "v1",
                                                                               "admin",
                                                                               "orders",
                                                                               "{id}"
                                                                           ],
                                                                  "variable":  [
                                                                                   {
                                                                                       "key":  "id",
                                                                                       "value":  ""
                                                                                   }
                                                                               ]
                                                              }
                                                  }
                                  },
                                  {
                                      "name":  "PUT /api/v1/admin/orders/{id}/status",
                                      "request":  {
                                                      "method":  "PUT",
                                                      "header":  [

                                                                 ],
                                                      "url":  {
                                                                  "raw":  "{{baseUrl}}/api/v1/admin/orders/{id}/status",
                                                                  "host":  [
                                                                               "{{baseUrl}}"
                                                                           ],
                                                                  "path":  [
                                                                               "api",
                                                                               "v1",
                                                                               "admin",
                                                                               "orders",
                                                                               "{id}",
                                                                               "status"
                                                                           ],
                                                                  "variable":  [
                                                                                   {
                                                                                       "key":  "id",
                                                                                       "value":  ""
                                                                                   }
                                                                               ]
                                                              }
                                                  }
                                  },
                                  {
                                      "name":  "GET /api/v1/admin/orders/recent",
                                      "request":  {
                                                      "method":  "GET",
                                                      "header":  [

                                                                 ],
                                                      "url":  {
                                                                  "raw":  "{{baseUrl}}/api/v1/admin/orders/recent",
                                                                  "host":  [
                                                                               "{{baseUrl}}"
                                                                           ],
                                                                  "path":  [
                                                                               "api",
                                                                               "v1",
                                                                               "admin",
                                                                               "orders",
                                                                               "recent"
                                                                           ]
                                                              }
                                                  }
                                  },
                                  {
                                      "name":  "GET /api/v1/admin/users",
                                      "request":  {
                                                      "method":  "GET",
                                                      "header":  [

                                                                 ],
                                                      "url":  {
                                                                  "raw":  "{{baseUrl}}/api/v1/admin/users",
                                                                  "host":  [
                                                                               "{{baseUrl}}"
                                                                           ],
                                                                  "path":  [
                                                                               "api",
                                                                               "v1",
                                                                               "admin",
                                                                               "users"
                                                                           ]
                                                              }
                                                  }
                                  },
                                  {
                                      "name":  "PUT /api/v1/admin/users/{id}/role",
                                      "request":  {
                                                      "method":  "PUT",
                                                      "header":  [

                                                                 ],
                                                      "url":  {
                                                                  "raw":  "{{baseUrl}}/api/v1/admin/users/{id}/role",
                                                                  "host":  [
                                                                               "{{baseUrl}}"
                                                                           ],
                                                                  "path":  [
                                                                               "api",
                                                                               "v1",
                                                                               "admin",
                                                                               "users",
                                                                               "{id}",
                                                                               "role"
                                                                           ],
                                                                  "variable":  [
                                                                                   {
                                                                                       "key":  "id",
                                                                                       "value":  ""
                                                                                   }
                                                                               ]
                                                              }
                                                  }
                                  },
                                  {
                                      "name":  "GET /api/v1/admin/returns",
                                      "request":  {
                                                      "method":  "GET",
                                                      "header":  [

                                                                 ],
                                                      "url":  {
                                                                  "raw":  "{{baseUrl}}/api/v1/admin/returns",
                                                                  "host":  [
                                                                               "{{baseUrl}}"
                                                                           ],
                                                                  "path":  [
                                                                               "api",
                                                                               "v1",
                                                                               "admin",
                                                                               "returns"
                                                                           ]
                                                              }
                                                  }
                                  },
                                  {
                                      "name":  "POST /api/v1/admin/returns/{returnId}/process",
                                      "request":  {
                                                      "method":  "POST",
                                                      "header":  [

                                                                 ],
                                                      "url":  {
                                                                  "raw":  "{{baseUrl}}/api/v1/admin/returns/{returnId}/process",
                                                                  "host":  [
                                                                               "{{baseUrl}}"
                                                                           ],
                                                                  "path":  [
                                                                               "api",
                                                                               "v1",
                                                                               "admin",
                                                                               "returns",
                                                                               "{returnId}",
                                                                               "process"
                                                                           ],
                                                                  "variable":  [
                                                                                   {
                                                                                       "key":  "returnId",
                                                                                       "value":  ""
                                                                                   }
                                                                               ]
                                                              }
                                                  }
                                  },
                                  {
                                      "name":  "GET /api/v1/admin/analytics",
                                      "request":  {
                                                      "method":  "GET",
                                                      "header":  [

                                                                 ],
                                                      "url":  {
                                                                  "raw":  "{{baseUrl}}/api/v1/admin/analytics",
                                                                  "host":  [
                                                                               "{{baseUrl}}"
                                                                           ],
                                                                  "path":  [
                                                                               "api",
                                                                               "v1",
                                                                               "admin",
                                                                               "analytics"
                                                                           ]
                                                              }
                                                  }
                                  },
                                  {
                                      "name":  "GET /api/v1/admin/products/top",
                                      "request":  {
                                                      "method":  "GET",
                                                      "header":  [

                                                                 ],
                                                      "url":  {
                                                                  "raw":  "{{baseUrl}}/api/v1/admin/products/top",
                                                                  "host":  [
                                                                               "{{baseUrl}}"
                                                                           ],
                                                                  "path":  [
                                                                               "api",
                                                                               "v1",
                                                                               "admin",
                                                                               "products",
                                                                               "top"
                                                                           ]
                                                              }
                                                  }
                                  }
                              ]
                 },
                 {
                     "name":  "auth",
                     "item":  [
                                  {
                                      "name":  "POST /api/v1/auth/register",
                                      "request":  {
                                                      "method":  "POST",
                                                      "header":  [

                                                                 ],
                                                      "url":  {
                                                                  "raw":  "{{baseUrl}}/api/v1/auth/register",
                                                                  "host":  [
                                                                               "{{baseUrl}}"
                                                                           ],
                                                                  "path":  [
                                                                               "api",
                                                                               "v1",
                                                                               "auth",
                                                                               "register"
                                                                           ]
                                                              }
                                                  }
                                  },
                                  {
                                      "name":  "POST /api/v1/auth/login",
                                      "request":  {
                                                      "method":  "POST",
                                                      "header":  [

                                                                 ],
                                                      "url":  {
                                                                  "raw":  "{{baseUrl}}/api/v1/auth/login",
                                                                  "host":  [
                                                                               "{{baseUrl}}"
                                                                           ],
                                                                  "path":  [
                                                                               "api",
                                                                               "v1",
                                                                               "auth",
                                                                               "login"
                                                                           ]
                                                              }
                                                  }
                                  },
                                  {
                                      "name":  "POST /api/v1/auth/refresh",
                                      "request":  {
                                                      "method":  "POST",
                                                      "header":  [

                                                                 ],
                                                      "url":  {
                                                                  "raw":  "{{baseUrl}}/api/v1/auth/refresh",
                                                                  "host":  [
                                                                               "{{baseUrl}}"
                                                                           ],
                                                                  "path":  [
                                                                               "api",
                                                                               "v1",
                                                                               "auth",
                                                                               "refresh"
                                                                           ]
                                                              }
                                                  }
                                  }
                              ]
                 },
                 {
                     "name":  "cart",
                     "item":  [
                                  {
                                      "name":  "GET /api/v1/cart/",
                                      "request":  {
                                                      "method":  "GET",
                                                      "header":  [

                                                                 ],
                                                      "url":  {
                                                                  "raw":  "{{baseUrl}}/api/v1/cart/",
                                                                  "host":  [
                                                                               "{{baseUrl}}"
                                                                           ],
                                                                  "path":  [
                                                                               "api",
                                                                               "v1",
                                                                               "cart"
                                                                           ]
                                                              }
                                                  }
                                  },
                                  {
                                      "name":  "DELETE /api/v1/cart/",
                                      "request":  {
                                                      "method":  "DELETE",
                                                      "header":  [

                                                                 ],
                                                      "url":  {
                                                                  "raw":  "{{baseUrl}}/api/v1/cart/",
                                                                  "host":  [
                                                                               "{{baseUrl}}"
                                                                           ],
                                                                  "path":  [
                                                                               "api",
                                                                               "v1",
                                                                               "cart"
                                                                           ]
                                                              }
                                                  }
                                  },
                                  {
                                      "name":  "GET /api/v1/cart/validate",
                                      "request":  {
                                                      "method":  "GET",
                                                      "header":  [

                                                                 ],
                                                      "url":  {
                                                                  "raw":  "{{baseUrl}}/api/v1/cart/validate",
                                                                  "host":  [
                                                                               "{{baseUrl}}"
                                                                           ],
                                                                  "path":  [
                                                                               "api",
                                                                               "v1",
                                                                               "cart",
                                                                               "validate"
                                                                           ]
                                                              }
                                                  }
                                  },
                                  {
                                      "name":  "POST /api/v1/cart/items",
                                      "request":  {
                                                      "method":  "POST",
                                                      "header":  [

                                                                 ],
                                                      "url":  {
                                                                  "raw":  "{{baseUrl}}/api/v1/cart/items",
                                                                  "host":  [
                                                                               "{{baseUrl}}"
                                                                           ],
                                                                  "path":  [
                                                                               "api",
                                                                               "v1",
                                                                               "cart",
                                                                               "items"
                                                                           ]
                                                              }
                                                  }
                                  },
                                  {
                                      "name":  "PUT /api/v1/cart/items/{itemId}",
                                      "request":  {
                                                      "method":  "PUT",
                                                      "header":  [

                                                                 ],
                                                      "url":  {
                                                                  "raw":  "{{baseUrl}}/api/v1/cart/items/{itemId}",
                                                                  "host":  [
                                                                               "{{baseUrl}}"
                                                                           ],
                                                                  "path":  [
                                                                               "api",
                                                                               "v1",
                                                                               "cart",
                                                                               "items",
                                                                               "{itemId}"
                                                                           ],
                                                                  "variable":  [
                                                                                   {
                                                                                       "key":  "itemId",
                                                                                       "value":  ""
                                                                                   }
                                                                               ]
                                                              }
                                                  }
                                  },
                                  {
                                      "name":  "DELETE /api/v1/cart/items/{itemId}",
                                      "request":  {
                                                      "method":  "DELETE",
                                                      "header":  [

                                                                 ],
                                                      "url":  {
                                                                  "raw":  "{{baseUrl}}/api/v1/cart/items/{itemId}",
                                                                  "host":  [
                                                                               "{{baseUrl}}"
                                                                           ],
                                                                  "path":  [
                                                                               "api",
                                                                               "v1",
                                                                               "cart",
                                                                               "items",
                                                                               "{itemId}"
                                                                           ],
                                                                  "variable":  [
                                                                                   {
                                                                                       "key":  "itemId",
                                                                                       "value":  ""
                                                                                   }
                                                                               ]
                                                              }
                                                  }
                                  }
                              ]
                 },
                 {
                     "name":  "health",
                     "item":  [
                                  {
                                      "name":  "GET /api/v1/health/",
                                      "request":  {
                                                      "method":  "GET",
                                                      "header":  [

                                                                 ],
                                                      "url":  {
                                                                  "raw":  "{{baseUrl}}/api/v1/health/",
                                                                  "host":  [
                                                                               "{{baseUrl}}"
                                                                           ],
                                                                  "path":  [
                                                                               "api",
                                                                               "v1",
                                                                               "health"
                                                                           ]
                                                              }
                                                  }
                                  }
                              ]
                 },
                 {
                     "name":  "metrics",
                     "item":  [
                                  {
                                      "name":  "GET /api/v1/metrics/",
                                      "request":  {
                                                      "method":  "GET",
                                                      "header":  [

                                                                 ],
                                                      "url":  {
                                                                  "raw":  "{{baseUrl}}/api/v1/metrics/",
                                                                  "host":  [
                                                                               "{{baseUrl}}"
                                                                           ],
                                                                  "path":  [
                                                                               "api",
                                                                               "v1",
                                                                               "metrics"
                                                                           ]
                                                              }
                                                  }
                                  }
                              ]
                 },
                 {
                     "name":  "orders",
                     "item":  [
                                  {
                                      "name":  "GET /api/v1/orders/",
                                      "request":  {
                                                      "method":  "GET",
                                                      "header":  [

                                                                 ],
                                                      "url":  {
                                                                  "raw":  "{{baseUrl}}/api/v1/orders/",
                                                                  "host":  [
                                                                               "{{baseUrl}}"
                                                                           ],
                                                                  "path":  [
                                                                               "api",
                                                                               "v1",
                                                                               "orders"
                                                                           ]
                                                              }
                                                  }
                                  },
                                  {
                                      "name":  "POST /api/v1/orders/",
                                      "request":  {
                                                      "method":  "POST",
                                                      "header":  [

                                                                 ],
                                                      "url":  {
                                                                  "raw":  "{{baseUrl}}/api/v1/orders/",
                                                                  "host":  [
                                                                               "{{baseUrl}}"
                                                                           ],
                                                                  "path":  [
                                                                               "api",
                                                                               "v1",
                                                                               "orders"
                                                                           ]
                                                              }
                                                  }
                                  },
                                  {
                                      "name":  "GET /api/v1/orders/{id}",
                                      "request":  {
                                                      "method":  "GET",
                                                      "header":  [

                                                                 ],
                                                      "url":  {
                                                                  "raw":  "{{baseUrl}}/api/v1/orders/{id}",
                                                                  "host":  [
                                                                               "{{baseUrl}}"
                                                                           ],
                                                                  "path":  [
                                                                               "api",
                                                                               "v1",
                                                                               "orders",
                                                                               "{id}"
                                                                           ],
                                                                  "variable":  [
                                                                                   {
                                                                                       "key":  "id",
                                                                                       "value":  ""
                                                                                   }
                                                                               ]
                                                              }
                                                  }
                                  },
                                  {
                                      "name":  "PUT /api/v1/orders/{id}/cancel",
                                      "request":  {
                                                      "method":  "PUT",
                                                      "header":  [

                                                                 ],
                                                      "url":  {
                                                                  "raw":  "{{baseUrl}}/api/v1/orders/{id}/cancel",
                                                                  "host":  [
                                                                               "{{baseUrl}}"
                                                                           ],
                                                                  "path":  [
                                                                               "api",
                                                                               "v1",
                                                                               "orders",
                                                                               "{id}",
                                                                               "cancel"
                                                                           ],
                                                                  "variable":  [
                                                                                   {
                                                                                       "key":  "id",
                                                                                       "value":  ""
                                                                                   }
                                                                               ]
                                                              }
                                                  }
                                  },
                                  {
                                      "name":  "GET /api/v1/orders/{id}/payment",
                                      "request":  {
                                                      "method":  "GET",
                                                      "header":  [

                                                                 ],
                                                      "url":  {
                                                                  "raw":  "{{baseUrl}}/api/v1/orders/{id}/payment",
                                                                  "host":  [
                                                                               "{{baseUrl}}"
                                                                           ],
                                                                  "path":  [
                                                                               "api",
                                                                               "v1",
                                                                               "orders",
                                                                               "{id}",
                                                                               "payment"
                                                                           ],
                                                                  "variable":  [
                                                                                   {
                                                                                       "key":  "id",
                                                                                       "value":  ""
                                                                                   }
                                                                               ]
                                                              }
                                                  }
                                  }
                              ]
                 },
                 {
                     "name":  "payments",
                     "item":  [
                                  {
                                      "name":  "POST /api/v1/payments/",
                                      "request":  {
                                                      "method":  "POST",
                                                      "header":  [

                                                                 ],
                                                      "url":  {
                                                                  "raw":  "{{baseUrl}}/api/v1/payments/",
                                                                  "host":  [
                                                                               "{{baseUrl}}"
                                                                           ],
                                                                  "path":  [
                                                                               "api",
                                                                               "v1",
                                                                               "payments"
                                                                           ]
                                                              }
                                                  }
                                  },
                                  {
                                      "name":  "POST /api/v1/payments/{id}/verify",
                                      "request":  {
                                                      "method":  "POST",
                                                      "header":  [

                                                                 ],
                                                      "url":  {
                                                                  "raw":  "{{baseUrl}}/api/v1/payments/{id}/verify",
                                                                  "host":  [
                                                                               "{{baseUrl}}"
                                                                           ],
                                                                  "path":  [
                                                                               "api",
                                                                               "v1",
                                                                               "payments",
                                                                               "{id}",
                                                                               "verify"
                                                                           ],
                                                                  "variable":  [
                                                                                   {
                                                                                       "key":  "id",
                                                                                       "value":  ""
                                                                                   }
                                                                               ]
                                                              }
                                                  }
                                  }
                              ]
                 },
                 {
                     "name":  "products",
                     "item":  [
                                  {
                                      "name":  "GET /api/v1/products/",
                                      "request":  {
                                                      "method":  "GET",
                                                      "header":  [

                                                                 ],
                                                      "url":  {
                                                                  "raw":  "{{baseUrl}}/api/v1/products/",
                                                                  "host":  [
                                                                               "{{baseUrl}}"
                                                                           ],
                                                                  "path":  [
                                                                               "api",
                                                                               "v1",
                                                                               "products"
                                                                           ]
                                                              }
                                                  }
                                  },
                                  {
                                      "name":  "GET /api/v1/products/{id}",
                                      "request":  {
                                                      "method":  "GET",
                                                      "header":  [

                                                                 ],
                                                      "url":  {
                                                                  "raw":  "{{baseUrl}}/api/v1/products/{id}",
                                                                  "host":  [
                                                                               "{{baseUrl}}"
                                                                           ],
                                                                  "path":  [
                                                                               "api",
                                                                               "v1",
                                                                               "products",
                                                                               "{id}"
                                                                           ],
                                                                  "variable":  [
                                                                                   {
                                                                                       "key":  "id",
                                                                                       "value":  ""
                                                                                   }
                                                                               ]
                                                              }
                                                  }
                                  }
                              ]
                 },
                 {
                     "name":  "ready",
                     "item":  [
                                  {
                                      "name":  "GET /api/v1/ready/",
                                      "request":  {
                                                      "method":  "GET",
                                                      "header":  [

                                                                 ],
                                                      "url":  {
                                                                  "raw":  "{{baseUrl}}/api/v1/ready/",
                                                                  "host":  [
                                                                               "{{baseUrl}}"
                                                                           ],
                                                                  "path":  [
                                                                               "api",
                                                                               "v1",
                                                                               "ready"
                                                                           ]
                                                              }
                                                  }
                                  }
                              ]
                 },
                 {
                     "name":  "returns",
                     "item":  [
                                  {
                                      "name":  "POST /api/v1/returns/",
                                      "request":  {
                                                      "method":  "POST",
                                                      "header":  [

                                                                 ],
                                                      "url":  {
                                                                  "raw":  "{{baseUrl}}/api/v1/returns/",
                                                                  "host":  [
                                                                               "{{baseUrl}}"
                                                                           ],
                                                                  "path":  [
                                                                               "api",
                                                                               "v1",
                                                                               "returns"
                                                                           ]
                                                              }
                                                  }
                                  },
                                  {
                                      "name":  "GET /api/v1/returns/",
                                      "request":  {
                                                      "method":  "GET",
                                                      "header":  [

                                                                 ],
                                                      "url":  {
                                                                  "raw":  "{{baseUrl}}/api/v1/returns/",
                                                                  "host":  [
                                                                               "{{baseUrl}}"
                                                                           ],
                                                                  "path":  [
                                                                               "api",
                                                                               "v1",
                                                                               "returns"
                                                                           ]
                                                              }
                                                  }
                                  },
                                  {
                                      "name":  "GET /api/v1/returns/{id}",
                                      "request":  {
                                                      "method":  "GET",
                                                      "header":  [

                                                                 ],
                                                      "url":  {
                                                                  "raw":  "{{baseUrl}}/api/v1/returns/{id}",
                                                                  "host":  [
                                                                               "{{baseUrl}}"
                                                                           ],
                                                                  "path":  [
                                                                               "api",
                                                                               "v1",
                                                                               "returns",
                                                                               "{id}"
                                                                           ],
                                                                  "variable":  [
                                                                                   {
                                                                                       "key":  "id",
                                                                                       "value":  ""
                                                                                   }
                                                                               ]
                                                              }
                                                  }
                                  }
                              ]
                 },
                 {
                     "name":  "users",
                     "item":  [
                                  {
                                      "name":  "GET /api/v1/users/profile",
                                      "request":  {
                                                      "method":  "GET",
                                                      "header":  [

                                                                 ],
                                                      "url":  {
                                                                  "raw":  "{{baseUrl}}/api/v1/users/profile",
                                                                  "host":  [
                                                                               "{{baseUrl}}"
                                                                           ],
                                                                  "path":  [
                                                                               "api",
                                                                               "v1",
                                                                               "users",
                                                                               "profile"
                                                                           ]
                                                              }
                                                  }
                                  },
                                  {
                                      "name":  "PUT /api/v1/users/profile",
                                      "request":  {
                                                      "method":  "PUT",
                                                      "header":  [

                                                                 ],
                                                      "url":  {
                                                                  "raw":  "{{baseUrl}}/api/v1/users/profile",
                                                                  "host":  [
                                                                               "{{baseUrl}}"
                                                                           ],
                                                                  "path":  [
                                                                               "api",
                                                                               "v1",
                                                                               "users",
                                                                               "profile"
                                                                           ]
                                                              }
                                                  }
                                  },
                                  {
                                      "name":  "PUT /api/v1/users/change-password",
                                      "request":  {
                                                      "method":  "PUT",
                                                      "header":  [

                                                                 ],
                                                      "url":  {
                                                                  "raw":  "{{baseUrl}}/api/v1/users/change-password",
                                                                  "host":  [
                                                                               "{{baseUrl}}"
                                                                           ],
                                                                  "path":  [
                                                                               "api",
                                                                               "v1",
                                                                               "users",
                                                                               "change-password"
                                                                           ]
                                                              }
                                                  }
                                  }
                              ]
                 }
             ],
    "variable":  [
                     {
                         "key":  "baseUrl",
                         "value":  "http://localhost:3000"
                     }
                 ]
}
